smpaul/__init__.py
smpaul/main.py
smpaul-0.1.5.dist-info/METADATA
smpaul-0.1.5.dist-info/WHEEL
smpaul-0.1.5.dist-info/top_level.txt
smpaul-0.1.5.dist-info/RECORD
